{
  "type": "Mission",
  "missionType": "Headquarters",
  "unique": true,
  "title": "Mouth of the Wormhole",
  "subtitle": "Deep Space 9",
  "quadrant": "Alpha",
  "span": 1,
  "points": 0,
  "keywords": [
    "Region: Bajor System"
  ],
  "affiliationsText": "Bajoran/Federation Headquarters",
  "abilities": [
    {
      "text": "You may play [DS9] cards, [NA] cards, and equipment at this mission.",
      "type": "headquarterRequirements",
      "filter": "or(icon(DS9),icon(NA),type(equipment))"
    },
    {
      "text": "When any player is about to move a ship between this mission and a [GQ] mission, do not add 2 to the span total of those missions.",
      "type": "trigger",
      "condition": "playerAboutToMove(any, from(self), to(icon(GQ)))",
      "effect": [
        {
          "type": "cancelQuadrantPenalty"
        }
      ]
    }
  ],
  "lore": "[b]Deep Space 9:[/b] \"...this has become my home.\""
}